[
  {
    "left": "portugal",
    "right": "croatia",
    "datetime": "2026-07-03T02:00"
  },
  {
    "left": "switzerland",
    "right": "algeria",
    "datetime": "2026-07-03T06:00"
  },
  {
    "left": "australia",
    "right": "egypt",
    "datetime": "2026-07-03T21:00"
  },
  {
    "left": "argentina",
    "right": "cape-verde",
    "datetime": "2026-07-04T01:00"
  },
  {
    "left": "colombia",
    "right": "ghana",
    "datetime": "2026-07-04T04:30"
  },
  {
    "left": "canada",
    "right": "morocco",
    "datetime": "2026-07-04T20:00"
  }
]
